noject/__init__.py
noject/builder.py
noject/collector.py
noject-0.1.0.dist-info/WHEEL
noject-0.1.0.dist-info/METADATA
noject-0.1.0.dist-info/RECORD
